strictus/__init__.py
strictus/core.py
strictus-1.0.2.dist-info/METADATA
strictus-1.0.2.dist-info/WHEEL
strictus-1.0.2.dist-info/top_level.txt
strictus-1.0.2.dist-info/RECORD
