Metadata-Version: 2.1
Name: strictus
Version: 1.0.2
Summary: Strictus (a rewrite of Strictus Dictus)
Home-page: https://github.com/jbasko/strictus
Author: Jazeps Basko
Author-email: jazeps.basko@gmail.com
Maintainer: Jazeps Basko
Maintainer-email: jazeps.basko@gmail.com
License: MIT
Keywords: nested schema dictionary attribute attrdict type hinting typing annotations
Platform: UNKNOWN
Classifier: Development Status :: 4 - Beta
Classifier: Intended Audience :: Developers
Classifier: Topic :: Software Development :: Libraries
Classifier: Programming Language :: Python
Classifier: Programming Language :: Python :: 3
Classifier: Programming Language :: Python :: 3.7
Classifier: License :: OSI Approved :: MIT License
Requires-Python: >=3.7.0
Requires-Dist: cached-property
